pystorm/__init__.py
pystorm/version.py
pystorm/connectivity/__init__.py
pystorm/connectivity/amplitude_envelope_correlation.py
pystorm/connectivity/pli.py
pystorm/signal_processing/__init__.py
pystorm/signal_processing/band_filter.py
pystorm/timefreq/PAC.py
pystorm/timefreq/__init__.py
pystorm/timefreq/analytical_signal.py
pystorm/timefreq/fft.py
pystorm/timefreq/morlet_wavelets.py
pystorm/timefreq/welch_psd.py
pystorm/utils/__init__.py
pystorm/utils/minitorch.py
pystorm/utils/time_series_utils.py
pystorm3-0.1.20.dist-info/licenses/LICENSE
pystorm3-0.1.20.dist-info/METADATA
pystorm3-0.1.20.dist-info/WHEEL
pystorm3-0.1.20.dist-info/top_level.txt
pystorm3-0.1.20.dist-info/RECORD
