Metadata-Version: 2.4
Name: pystorm3
Version: 0.1.20
Summary: Python implementation of some Brainstorm functions
Home-page: https://github.com/NeuroLife77/pystorm
Author: Dominic Boutet
Author-email: dominic.boutet@mail.mcgill.ca
Maintainer: Dominic Boutet
Maintainer-email: dominic.boutet@mail.mcgill.ca
License: GPL-3.0 license
Keywords: neuroscience,neuroimaging,neural oscillations,time series analysis,time frequency analysis
Classifier: Development Status :: 1 - Planning
Classifier: Intended Audience :: Science/Research
Classifier: Topic :: Scientific/Engineering
Classifier: Operating System :: Unix
Classifier: Programming Language :: Python
Requires-Python: >=3.9
License-File: LICENSE
Requires-Dist: torch>=2.2.0
Requires-Dist: numpy>=1.26
Requires-Dist: scipy>=1.13.0
Requires-Dist: torchaudio>=2.2.0
Requires-Dist: numba>=0.59
Dynamic: author
Dynamic: author-email
Dynamic: classifier
Dynamic: description
Dynamic: description-content-type
Dynamic: home-page
Dynamic: keywords
Dynamic: license
Dynamic: license-file
Dynamic: maintainer
Dynamic: maintainer-email
Dynamic: requires-dist
Dynamic: requires-python
Dynamic: summary
